IR_types/alu_ctrl.sv
`timescale 1ns/10ps

module alu_ctrl(
  	
  	input logic  [1:0] alu_op,
  	input logic  [2:0] funct3,
  	input logic  	   funct7_5,
  	output logic [3:0] alu_ctrl
);
  
  always_comb begin
    case(alu_op)
      2'b00: alu_ctrl = 4'b0010;
      2'b01: alu_ctrl = 4'b0110;
      2'b10: begin
        case(funct3)
          3'b000: alu_ctrl = (funct7_5 == 1'b1) ? 4'b0110 : 4'b0010;
          3'b001: alu_ctrl = 4'b0100;
          3'b010: alu_ctrl = 4'b1000;
          3'b011: alu_ctrl = 4'b1001;
          3'b100: alu_ctrl = 4'b0011;
          3'b101: alu_ctrl = (funct7_5 == 1'b1) ? 4'b0111 : 4'b0101;
          3'b110: alu_ctrl = 4'b0001;
          3'b111: alu_ctrl = 4'b0000;
          default: alu_ctrl = 4'b0000;
         endcase
      end
      2'b11: begin
        case(funct3)
          3'b000: alu_ctrl = 4'b0010;
          3'b001: alu_ctrl = 4'b0100;
          3'b010: alu_ctrl = 4'b1000;
          3'b011: alu_ctrl = 4'b1001;
          3'b100: alu_ctrl = 4'b0011;
          3'b101: alu_ctrl = (funct7_5 == 1'b1) ? 4'b0111 : 4'b0101;
          3'b110: alu_ctrl = 4'b0001;
          3'b111: alu_ctrl = 4'b0000;
        endcase
      end
      default: alu_ctrl = 4'b0000;
    endcase
  end
endmodule

riscv_core_implementation/IRJS_types/alu.sv
`timescale 1ns/10ps
module alu (
    input  logic [31:0] a,
    input  logic [31:0] b,
    input  logic [3:0]  alu_ctrl,
    output logic [31:0] alu_result,
    output logic        zero
);

    always_comb begin
        case (alu_ctrl)
            4'b0000: alu_result = a & b;
            4'b0001: alu_result = a | b;
            4'b0010: alu_result = a + b;
            4'b0110: alu_result = a - b;
            4'b0011: alu_result = a ^ b;
            4'b0100: alu_result = a << b[4:0];
            4'b0101: alu_result = a >> b[4:0];
            4'b0111: alu_result = $signed(a) >>> b[4:0];
            4'b1000: alu_result = ($signed(a) < $signed(b)) ? 32'd1 : 32'd0;
            4'b1001: alu_result = (a < b) ? 32'd1 : 32'd0;
            default: alu_result = 32'b0;
        endcase
    end

    assign zero = (alu_result == 32'b0) ? 1'b1 : 1'b0;

endmodule

riscv_core_implementation/IRJSBU_types/main_ctrl.sv
`timescale 1ns/10ps

module main_ctrl (
  	input logic  [6:0]  opcode,
  	output logic 		reg_write,
  	output logic [1:0]  alu_op,
  	output logic 		alu_src,
	output logic 		mem_read,
  	output logic 		mem_to_reg,
  	output logic 		mem_write,
  	output logic        jump,
  	output logic        branch,
    output logic        a_sel
);
  
  
  always_comb begin
    

    reg_write  = 1'b0;
    alu_op 	   = 2'b00;
    alu_src    = 1'b0;
    mem_read   = 1'b0;
    mem_to_reg = 1'b0;
    mem_write  = 1'b0;
    jump       = 1'b0;
    branch     = 1'b0;
    a_sel      = 1'b0;
    
    case(opcode)
        7'b0110011: begin //R type
          reg_write  = 1'b1;
          alu_src    = 1'b0;
          alu_op     = 2'b10;
        end

        7'b0010011: begin //I type arithmetic
          alu_src    = 1'b1;
          reg_write  = 1'b1;
          alu_op     = 2'b11;
        end


        7'b0000011: begin //I type loads
          alu_src    = 1'b1;
          mem_to_reg = 1'b1;
          reg_write  = 1'b1;
          mem_read   = 1'b1;
          alu_op     = 2'b00;
        end


        7'b0100011: begin //S type
          reg_write  = 1'b0;
          alu_src    = 1'b1;
          mem_write  = 1'b1;
          alu_op     = 2'b00;
        end
        
        
        7'b1101111: begin //J type (jal)
            reg_write  = 1'b1;
            jump       = 1'b1;
        end


        7'b1100111: begin //I type jump (jalr)
            reg_write  = 1'b1;    
            jump       = 1'b1;    
            alu_src    = 1'b1;
            alu_op     = 2'b00;
        end
        
        7'b1100011: begin // B-Type (Branches)
          branch     = 1'b1;
          alu_op     = 2'b01;
        end
        
        7'b0110111: begin // U-Type (lui)
          reg_write  = 1'b1;
          alu_src    = 1'b1; 
          a_sel      = 1'b1;
          alu_op     = 2'b00; 
        end
        
        7'b0010111: begin // U-Type (auipc)
          reg_write  = 1'b1;
          alu_src    = 1'b1;
          a_sel      = 1'b1;
          alu_op     = 2'b00;
        end


        default: ;
      
     endcase
    
   end
  
endmodule

IR_types/imm_gen.sv
module imm_gen (
    input  logic [31:0] inst,
    output logic [31:0] imm
);


    assign imm = {{20{inst[31]}}, inst[31:20]};

endmodule

IRJS_types/reg_file.sv
module reg_file (
    input  logic        clk,
    input  logic        RegWEn,
    input logic rst,
    input  logic [4:0]  rs1,
    input  logic [4:0]  rs2,
    input  logic [4:0]  rsW,
    input  logic [31:0] dataW,
    output logic [31:0] data1,
    output logic [31:0] data2
);

    logic [31:0] registers [31:0];


    assign data1 = (rs1 == 5'b00000) ? 32'b0 : registers[rs1];
    assign data2 = (rs2 == 5'b00000) ? 32'b0 : registers[rs2];

    always_ff @(posedge clk) begin
	  if (rst) begin
		for (int i = 0; i < 32; i++) begin
            	registers[i] = 32'b0;
        	end
	  end
        else if (RegWEn) begin
            if (rsW != 5'b00000) begin
                registers[rsW] <= dataW;
            end
        end
    end

endmodule

riscv_core_implementation/sourcecode/rtl/i_mem.sv
module i_mem (
    input  logic [31:0] addr,
    output logic [31:0] word
);


    logic [31:0] memory [0:63];


    initial begin
        $readmemh("instructions.mem", memory);
    end

    assign word = memory[addr[31:2]];

endmodule

riscv_core_implementation/sourcecode/rtl/IR_types/program_counter.sv
module program_counter (
    input  logic        clk,
    input  logic        rst,
    input  logic [31:0] pc_next,
    output logic [31:0] pc
);

    always_ff @(posedge clk or posedge rst) begin
        if (rst) begin
            pc <= 32'h0000_0000;
        end else begin
            pc <= pc_next;
        end
    end

endmodule

IR_types/riscv_top.sv
`timescale 1ns/10ps

module riscv_top (
  	input logic rst,
  	input logic clk
);
  
  

    logic [31:0] pc_current;
    logic [31:0] pc_next;
    logic [31:0] instruction;
    

  	logic [31:0] read_reg_data1;
  	logic [31:0] read_reg_data2;
    

    logic [31:0] imm_extended;
    logic [31:0] alu_operand_b;
    logic [31:0] alu_result;
    logic [3:0]  alu_ctrl_signal;
    logic        alu_zero;
    

    logic [1:0] alu_op;
    logic       alu_src;
    logic       reg_write;
  
  
  	assign pc_next = pc_current + 32'd4;
  
  	program_counter pc_inst (
      	.clk(clk),
      	.rst(rst),
      	.pc_next(pc_next),
      	.pc(pc_current)
    );
  	
  	
  	i_mem i_mem_inst (
      	.addr(pc_current),
      	.word(instruction)
  	);
  
  	reg_file reg_file_inst (
      	.clk(clk),
        .RegWEn(reg_write),
        .rst(rst),
        .rs1(instruction[19:15]),
      	.rs2(instruction[24:20]),
        .rsW(instruction[11:7]),
        .dataW(alu_result),
      	.data1(read_reg_data1),
      	.data2(read_reg_data2)
    );
  
  	imm_gen imm_gen_inst (
        .inst(instruction),
        .imm(imm_extended)
    );
  
  	main_ctrl main_ctrl_inst (
        .opcode(instruction[6:0]),
        .reg_write(reg_write),
        .alu_op(alu_op),
        .alu_src(alu_src)
        //.mem_read(),
        //.mem_to_reg(),
        //.mem_write()
  	);
  
  	assign alu_operand_b = (alu_src) ? imm_extended : read_reg_data2;
  
  	alu alu_inst (
        .a(read_reg_data1),
        .b(alu_operand_b),
        .alu_ctrl(alu_ctrl_signal),
        .alu_result(alu_result),
        .zero(alu_zero)
  	);
  
  	alu_ctrl alu_ctrl_inst (
        .alu_op(alu_op),
        .funct3(instruction[14:12]),
        .funct7_5(instruction[30]),
        .alu_ctrl(alu_ctrl_signal)
  	);
  
  
endmodule

riscv_core_implementation/IRJS_types/riscv_top_tb.sv
`timescale 1ns/10ps

module riscv_top_tb;

    // 1. Declare Testbench Signals
    logic clk;
    logic rst;

    // 2. Instantiate the Top-Level Processor (Device Under Test)
    riscv_top dut (
        .clk(clk),
        .rst(rst)
    );

    // 3. Clock Generation: 10ns period (100 MHz)
    always #5 clk = ~clk;

    // 4. Test Sequence
    initial begin
        $display("=================================================");
        $display("          Starting RISC-V Processor              ");
        $display("=================================================");
        
        // Initialize clock and assert reset
        clk = 0;
        rst = 1; 

        // Hold reset high for a few clock cycles to ensure 
        // the Program Counter (PC) and registers initialize to 0.
        #20;
        
        // De-assert reset to let the processor start fetching and executing
        rst = 0; 

        // Let the processor run for a set amount of time.
        // Adjust this duration based on how many instructions are in your i_mem.
        // (100ns = 10 instructions at 10ns per cycle)
        #200; 

        $display("=================================================");
        $display("          Simulation Complete                    ");
        $display("=================================================");
        $finish;
    end

endmodule

IRJS_types/project_IRJS_types/project_IRJS_types.sim/sim_1/behav/xsim/dump.vcd
$date
   Thu Jul 23 10:20:06 2026
$end
$version
  2019.1
$end
$timescale
  1ps
$end
$scope module riscv_top_tb $end
$var reg 1 ! rst $end
$var reg 1 " clk $end
$scope module dut $end
$var wire 1 # rst $end
$var wire 1 $ clk $end
$var reg 32 % pc_current [31:0] $end
$var reg 32 & pc_next [31:0] $end
$var reg 32 ' instruction [31:0] $end
$var reg 32 ( read_reg_data1 [31:0] $end
$var reg 32 ) read_reg_data2 [31:0] $end
$var reg 32 * imm_extended [31:0] $end
$var reg 32 + alu_operand_b [31:0] $end
$var reg 32 , alu_result [31:0] $end
$var reg 4 - alu_ctrl_signal [3:0] $end
$var reg 1 . alu_zero $end
$var reg 2 / alu_op [1:0] $end
$var reg 1 0 alu_src $end
$var reg 1 1 reg_write $end
$scope module pc_inst $end
$var wire 1 $ clk $end
$var wire 1 # rst $end
$var wire 32 2 pc_next [31:0] $end
$var reg 32 % pc [31:0] $end
$upscope $end
$scope module i_mem_inst $end
$var wire 32 3 addr [31:0] $end
$var reg 32 ' word [31:0] $end
$upscope $end
$scope module reg_file_inst $end
$var wire 1 $ clk $end
$var wire 1 4 RegWEn $end
$var wire 1 # rst $end
$var wire 5 5 rs1 [4:0] $end
$var wire 5 6 rs2 [4:0] $end
$var wire 5 7 rsW [4:0] $end
$var wire 32 8 dataW [31:0] $end
$var reg 32 ( data1 [31:0] $end
$var reg 32 ) data2 [31:0] $end
$scope begin Block21_3 $end
$var reg 32 9 i $end
$upscope $end
$upscope $end
$scope module imm_gen_inst $end
$var wire 32 : inst [31:0] $end
$var reg 32 * imm [31:0] $end
$upscope $end
$scope module main_ctrl_inst $end
$var wire 7 ; opcode [6:0] $end
$var reg 1 1 reg_write $end
$var reg 2 / alu_op [1:0] $end
$var reg 1 0 alu_src $end
$upscope $end
$scope module alu_inst $end
$var wire 32 < a [31:0] $end
$var wire 32 = b [31:0] $end
$var wire 4 > alu_ctrl [3:0] $end
$var reg 32 , alu_result [31:0] $end
$var reg 1 . zero $end
$upscope $end
$scope module alu_ctrl_inst $end
$var wire 2 ? alu_op [1:0] $end
$var wire 3 @ funct3 [2:0] $end
$var wire 1 A funct7_5 $end
$var reg 4 - alu_ctrl [3:0] $end
$upscope $end
$upscope $end
$upscope $end
$enddefinitions $end
#0
$dumpvars
1!
0"
1#
0$
b0 %
b100 &
b10100000000000010010011 '
b0 (
bx )
b101 *
b101 +
b101 ,
b10 -
0.
b0 /
10
11
b100 2
b0 3
14
b0 5
b101 6
b1 7
b101 8
b0 9
b10100000000000010010011 :
b10011 ;
b0 <
b101 =
b10 >
b0 ?
b0 @
0A
$end
#5000
1"
1$
b0 (
b0 )
b101 +
b100000 9
#10000
0"
0$
#15000
0!
1"
0#
1$
b100 %
b1000 &
b101000000000000100010011 '
b0 (
b0 )
b1010 *
b1010 +
b1010 ,
b1000 2
b100 3
b1010 6
b10 7
b1010 8
b101000000000000100010011 :
b1010 =
#20000
0"
0$
#25000
1"
1$
b1000 %
b1100 &
b1000001000000110110011 '
b101 (
b1010 )
b10 *
b1010 +
b1111 ,
b10 -
b10 /
00
11
b1100 2
b1000 3
b1 5
b10 6
b11 7
b1111 8
b1000001000000110110011 :
b110011 ;
b101 <
b10 ?
#30000
0"
0$
#35000
1"
1$
b1100 %
b10000 &
b1000000000100010000001000110011 '
b1010 (
b101 )
b10000000001 *
b101 +
b101 ,
b110 -
b10000 2
b1100 3
b10 5
b1 6
b100 7
b101 8
b1000000000100010000001000110011 :
b1010 <
b101 =
b110 >
1A
#40000
0"
0$
#45000
1"
1$
b10000 %
b10100 &
b11111111111100000000001010010011 '
b0 (
b0 )
b11111111111111111111111111111111 *
b11111111111111111111111111111111 +
b11111111111111111111111111111111 ,
b10 -
b0 /
10
11
b10100 2
b10000 3
b0 5
b11111 6
b101 7
b11111111111111111111111111111111 8
b11111111111100000000001010010011 :
b10011 ;
b0 <
b11111111111111111111111111111111 =
b10 >
b0 ?
#50000
0"
0$
#55000
1"
1$
b10100 %
b11000 &
b10100001111001100110011 '
b101 (
b11111111111111111111111111111111 )
b101 *
b11111111111111111111111111111111 +
b101 ,
b0 -
b10 /
00
11
b11000 2
b10100 3
b1 5
b101 6
b110 7
b101 8
b10100001111001100110011 :
b110011 ;
b101 <
b0 >
b10 ?
b111 @
0A
#60000
0"
0$
#65000
1"
1$
b11000 %
b11100 &
b1000001110001110110011 '
b101 (
b1010 )
b10 *
b1010 +
b1111 ,
b1 -
b11100 2
b11000 3
b10 6
b111 7
b1111 8
b1000001110001110110011 :
b1010 =
b1 >
b110 @
#70000
0"
0$
#75000
1"
1$
b11100 %
b100000 &
b1010000100000010000010011 '
b101 (
b0 )
b10100 *
b10100 +
b11001 ,
b10 -
b0 /
10
11
b100000 2
b11100 3
b100 5
b10100 6
b1000 7
b11001 8
b1010000100000010000010011 :
b10011 ;
b10100 =
b10 >
b0 ?
b0 @
#80000
0"
0$
#85000
1"
1$
b100000 %
b100100 &
b101000000010010110011 '
b11001 (
b101 )
b1 *
b101 +
b11110 ,
b10 -
b10 /
00
11
b100100 2
b100000 3
b1000 5
b1 6
b1001 7
b11110 8
b101000000010010110011 :
b110011 ;
b11001 <
b101 =
b10 ?
#90000
0"
0$
#95000
1"
1$
b100100 %
b101000 &
b1000000001001001000010100110011 '
b11110 (
b1010 )
b10000000010 *
b1010 +
b10100 ,
b110 -
b101000 2
b100100 3
b1001 5
b10 6
b1010 7
b10100 8
b1000000001001001000010100110011 :
b11110 <
b1010 =
b110 >
1A
#100000
0"
0$
#105000
1"
1$
b101000 %
b101100 &
bx '
bx (
bx )
bx *
bx +
bx ,
b10 -
x.
b0 /
00
01
b101100 2
b101000 3
04
bx 5
bx 6
bx 7
bx 8
bx :
bx ;
bx <
bx =
b10 >
b0 ?
bx @
xA
